LICENSE
README.md
setup.py
ninjax/__init__.py
ninjax/ninjax.py
ninjax.egg-info/PKG-INFO
ninjax.egg-info/SOURCES.txt
ninjax.egg-info/dependency_links.txt
ninjax.egg-info/requires.txt
ninjax.egg-info/top_level.txt
tests/test_attrs.py
tests/test_checkpoint.py
tests/test_cond.py
tests/test_grad.py
tests/test_init.py
tests/test_jit.py
tests/test_module.py
tests/test_scan.py
tests/test_variable.py