Metadata-Version: 2.1
Name: ninjax
Version: 2.5.0
Summary: Flexible Modules for JAX
Home-page: http://github.com/danijar/ninjax
Classifier: Intended Audience :: Science/Research
Classifier: License :: OSI Approved :: MIT License
Classifier: Programming Language :: Python :: 3
Classifier: Topic :: Scientific/Engineering :: Artificial Intelligence
License-File: LICENSE
